{
  "questIDLow:4": -7996701060940863901,
  "questIDHigh:4": -5011081735808925444,
  "tasks:9": {
    "0:10": {
      "allowCraft:1": 1,
      "allowAnvil:1": 0,
      "taskID:8": "bq_standard:crafting",
      "allowCraftedFromStatistics:1": 0,
      "index:3": 0,
      "requiredItems:9": {
        "0:10": {
          "Damage:2": 0,
          "id:8": "camping:sleepingBag",
          "OreDict:8": "",
          "Count:3": 1
        }
      },
      "partialMatch:1": 1,
      "allowSmelt:1": 1,
      "ignoreNBT:1": 1
    }
  },
  "preRequisites:9": {
    "0:10": {
      "questIDLow:4": 6,
      "questIDHigh:4": 0
    }
  },
  "rewards:9": {
    "0:10": {
      "index:3": 0,
      "rewards:9": {
        "0:10": {
          "Damage:2": 0,
          "id:8": "camping:parts",
          "OreDict:8": "",
          "Count:3": 3
        }
      },
      "rewardID:8": "bq_standard:item"
    }
  },
  "properties:10": {
    "betterquesting:10": {
      "visibility:8": "NORMAL",
      "icon:10": {
        "Damage:2": 0,
        "id:8": "camping:sleepingBag",
        "OreDict:8": "",
        "Count:3": 1
      },
      "repeatTime:3": -1,
      "isSilent:1": 0,
      "questLogic:8": "AND",
      "isMain:1": 0,
      "lockedProgress:1": 0,
      "repeat_relative:1": 1,
      "snd_update:8": "random.levelup",
      "name:8": "睡袋",
      "snd_complete:8": "random.levelup",
      "autoClaim:1": 0,
      "taskLogic:8": "AND",
      "simultaneous:1": 0,
      "globalShare:1": 0,
      "desc:8": "只是普通的[url]睡袋[/url]，但是可以设置重生点。"
    }
  }
}